setup.cfg
setup.py
nau_orchard.egg-info/PKG-INFO
nau_orchard.egg-info/SOURCES.txt
nau_orchard.egg-info/dependency_links.txt
nau_orchard.egg-info/entry_points.txt
nau_orchard.egg-info/requires.txt
nau_orchard.egg-info/top_level.txt
orchard/__init__.py
orchard/__main__.py
orchard/cli.py
orchard/_data/link.yaml
orchard/core/__init__.py
orchard/core/_branch.py
orchard/core/_configuration_file_reader.py
orchard/core/_generator.py
orchard/core/tests/__init__.py
orchard/core/tests/test_branch.py
orchard/core/tests/test_configuration_file_reader.py
orchard/core/tests/test_generator.py
orchard/file/__init__.py
orchard/file/_config.py
orchard/file/_link.py
orchard/file/_log.py
orchard/file/_yaml_file.py
orchard/file/tests/__init__.py
orchard/file/tests/test_config.py
orchard/file/tests/test_link.py
orchard/module/__init__.py
orchard/module/_argument.py
orchard/module/_module.py
orchard/module/tests/__init__.py
orchard/module/tests/test_argument.py
orchard/module/tests/test_module.py
orchard/tests/__init__.py
orchard/tests/test_cli.py