Metadata-Version: 1.1
Name: nau-orchard
Version: 0.0.3
Summary: A pipeline management generation tool
Home-page: https://github.com/acgt-tax-consultants/orchard
Author: AGTC Genetic Tax. Consultants
Author-email: blazer@nau.edu
License: UNKNOWN
Download-URL: https://github.com/acgt-tax-consultants/orchard/archive/0.1.tar.gz
Platform: UNKNOWN
